README.md
setup.py
torchsm/__init__.py
torchsm/sequential.py
torchsm.egg-info/PKG-INFO
torchsm.egg-info/SOURCES.txt
torchsm.egg-info/dependency_links.txt
torchsm.egg-info/requires.txt
torchsm.egg-info/top_level.txt
torchsm/layers/__init__.py
torchsm/layers/base_layer.py
torchsm/layers/recurrent_stigmem_layer.py
torchsm/layers/stigmem_layer.py