Metadata-Version: 2.1
Name: torchsm
Version: 0.1.0
Summary: Pytorch implementation of the Stigmergic Memory
Home-page: https://github.com/galatolofederico/torchsm
Author: Federico A. Galatolo
Author-email: federico.galatolo@ing.unipi.it
License: UNKNOWN
Platform: UNKNOWN
Classifier: Programming Language :: Python :: 3.6
Classifier: License :: OSI Approved :: GNU General Public License v3 (GPLv3)
Classifier: Operating System :: OS Independent
Classifier: Topic :: Scientific/Engineering :: Artificial Intelligence
Classifier: Intended Audience :: Science/Research
Classifier: Development Status :: 4 - Beta
